fhir_slicing/__init__.py
fhir_slicing/base.py
fhir_slicing/coding.py
fhir_slicing/element_array.py
fhir_slicing/extension.py
fhir_slicing/slice.py
fhir_slicing/slice_schema.py
fhir_slicing/typing.py
fhir_slicing/usage_context.py
fhir_slicing/utils.py
fhir_slicing-0.2.5.dist-info/METADATA
fhir_slicing-0.2.5.dist-info/WHEEL
fhir_slicing-0.2.5.dist-info/RECORD
