Metadata-Version: 2.4
Name: fhir-slicing
Version: 0.2.5
Summary: FHIR Slicing utilities build on top of Pydantic
Requires-Python: >=3.13
Requires-Dist: pydantic<3,>=2.10
